scatterem/__init__.py
scatterem/_modidx.py
scatterem/core.py
scatterem-0.0.10.dist-info/LICENSE
scatterem-0.0.10.dist-info/METADATA
scatterem-0.0.10.dist-info/WHEEL
scatterem-0.0.10.dist-info/entry_points.txt
scatterem-0.0.10.dist-info/top_level.txt
scatterem-0.0.10.dist-info/RECORD
